sparse_graphs/__init__.py
sparse_graphs/asym_graph.py
sparse_graphs/stale.py
sparse_graphs-0.0.2.dist-info/LICENSE
sparse_graphs-0.0.2.dist-info/METADATA
sparse_graphs-0.0.2.dist-info/WHEEL
sparse_graphs-0.0.2.dist-info/top_level.txt
sparse_graphs-0.0.2.dist-info/RECORD
