Metadata-Version: 2.1
Name: sparse-graphs
Version: 0.0.2
Summary: Efficient Implementation of Sparse Graphs with Numpy
Home-page: https://github.com/geyang/sparse-graphs
Author: Ge Yang
Author-email: ge.ike.yang@gmail.com
License: UNKNOWN
Platform: UNKNOWN
Requires-Dist: numpy
